lotr/__init__.py
lotr/lotr.py
nrh_lotr-0.0.3.dist-info/LICENSE.txt
nrh_lotr-0.0.3.dist-info/METADATA
nrh_lotr-0.0.3.dist-info/WHEEL
nrh_lotr-0.0.3.dist-info/top_level.txt
nrh_lotr-0.0.3.dist-info/RECORD
