Metadata-Version: 2.1
Name: nrh-lotr
Version: 0.0.3
Summary: lotR SDK for movies and quotes
Author-email: Nathan Hapeman <nhapeman@gmail.com>
License: MIT License
Requires-Python: >=3.9
License-File: LICENSE.txt
